drool/__init__.py
drool/operators.py
drool-0.0.5.dist-info/LICENSE
drool-0.0.5.dist-info/METADATA
drool-0.0.5.dist-info/WHEEL
drool-0.0.5.dist-info/RECORD
