Metadata-Version: 2.1
Name: drool
Version: 0.0.5
Summary: 
Author: dm
Author-email: git@defend.sh
Requires-Python: >=3.12,<4.0
Classifier: Programming Language :: Python :: 3
Classifier: Programming Language :: Python :: 3.12
Classifier: Programming Language :: Python :: 3.13
Requires-Dist: pydantic (==2.10.0)
